openstream/__init__.py
openstream/core.py
openstream-0.1.0.dist-info/METADATA
openstream-0.1.0.dist-info/WHEEL
openstream-0.1.0.dist-info/licenses/LICENSE
openstream-0.1.0.dist-info/RECORD
